tests/__init__.py
tests/test_weighted_choice.py
weighted_choice/__init__.py
weighted_choice/base.py
weighted_choice/cli.py
weighted_choice/exceptions.py
weighted_choice-0.1.0.dist-info/METADATA
weighted_choice-0.1.0.dist-info/RECORD
weighted_choice-0.1.0.dist-info/WHEEL
weighted_choice-0.1.0.dist-info/entry_points.txt
weighted_choice-0.1.0.dist-info/top_level.txt
