Metadata-Version: 2.1
Name: weighted-choice
Version: 0.1.0
Summary: Select items randomly from a list with weighted probability of selection
Home-page: https://github.com/dusktreader/weighted-choice
Author: Tucker Beck
Author-email: tucker.beck@gmail.com
License: MIT
Platform: UNKNOWN
Provides-Extra: dev
Requires-Dist: click
Provides-Extra: dev
Requires-Dist: flake8; extra == 'dev'
Requires-Dist: pytest; extra == 'dev'
Requires-Dist: sphinx; extra == 'dev'
Requires-Dist: sphinx-view; extra == 'dev'
